{"obj_name": "Greater Mystic Thrall", "body_part_renders": [702050, 702052, 702053, 702054, 702055, 702056, 702057, 702058, 702059, 702060, 702061, 702062, 702063, 702064, 702065, 702066, 702067], "render_data": {"702050": {"render_template": {"template_object_can_fade": true, "template_tracker": "NONE", "template_illuminated": false, "template_bone_length": 0.3540000021457672, "template_clip_map": 1, "template_light_two_side": 0, "template_cull_face": 1, "template_specular_map": 0, "template_shininess": 0.009999999776482582, "template_has_mesh": true, "template_mesh": {"mesh_set": [{"polymesh_id": 702051, "polymesh_decal": false, "polymesh_double_sided": false}]}}, "render_target_bone": "LOWERBACK", "render_scale": [1.0, 1.0, 1.0], "render_has_loc": 1, "render_loc": [0.0, 0.0, 0.0], "render_children": [], "render_has_texture_set": true, "render_texture_set": [{"texture_type": "COLOR_TEXTURE", "texture_data": {"texture_id": 702050, "texture_transparent": "ALPHA", "texture_compress": true, "texture_normal_map": false, "texture_detail_normal_map": false, "texture_create_mip_maps": true, "texture_wrap": true}}], "render_collides": true, "render_calculate_bounding_box": true, "render_nation_crest": false, "render_guild_crest": false, "render_bumped": false, "render_vp_active": false, "render_has_light_effects": false}, "702052": {"render_template": {"template_object_can_fade": true, "template_tracker": "NONE", "template_illuminated": false, "template_bone_length": 0.6419820189476013, "template_clip_map": 1, "template_light_two_side": 0, "template_cull_face": 1, "template_specular_map": 0, "template_shininess": 0.009999999776482582, "template_has_mesh": true, "template_mesh": {"mesh_set": [{"polymesh_id": 702052, "polymesh_decal": false, "polymesh_double_sided": false}]}}, "render_target_bone": "UPPERBACK", "render_scale": [1.0, 1.0, 1.0], "render_has_loc": 1, "render_loc": [0.0, 0.0, 0.0], "render_children": [], "render_has_texture_set": true, "render_texture_set": [{"texture_type": "COLOR_TEXTURE", "texture_data": {"texture_id": 702050, "texture_transparent": "ALPHA", "texture_compress": true, "texture_normal_map": false, "texture_detail_normal_map": false, "texture_create_mip_maps": true, "texture_wrap": true}}], "render_collides": true, "render_calculate_bounding_box": true, "render_nation_crest": false, "render_guild_crest": false, "render_bumped": false, "render_vp_active": false, "render_has_light_effects": false}, "702053": {"render_template": {"template_object_can_fade": true, "template_tracker": "NONE", "template_illuminated": false, "template_bone_length": 0.3459950089454651, "template_clip_map": 1, "template_light_two_side": 0, "template_cull_face": 1, "template_specular_map": 0, "template_shininess": 0.0, "template_has_mesh": true, "template_mesh": {"mesh_set": [{"polymesh_id": 702053, "polymesh_decal": false, "polymesh_double_sided": false}]}}, "render_target_bone": "RSHOULDERJOINT", "render_scale": [1.0, 1.0, 1.0], "render_has_loc": 1, "render_loc": [0.0, 0.0, 0.0], "render_children": [], "render_has_texture_set": false, "render_collides": true, "render_calculate_bounding_box": true, "render_nation_crest": false, "render_guild_crest": false, "render_bumped": false, "render_vp_active": false, "render_has_light_effects": false}, "702054": {"render_template": {"template_object_can_fade": true, "template_tracker": "NONE", "template_illuminated": false, "template_bone_length": 0.4759860038757324, "template_clip_map": 1, "template_light_two_side": 0, "template_cull_face": 1, "template_specular_map": 0, "template_shininess": 0.009999999776482582, "template_has_mesh": true, "template_mesh": {"mesh_set": [{"polymesh_id": 702054, "polymesh_decal": false, "polymesh_double_sided": false}]}}, "render_target_bone": "RHUMERUS", "render_scale": [1.0, 1.0, 1.0], "render_has_loc": 1, "render_loc": [0.0, 0.0, 0.0], "render_children": [], "render_has_texture_set": true, "render_texture_set": [{"texture_type": "COLOR_TEXTURE", "texture_data": {"texture_id": 702050, "texture_transparent": "ALPHA", "texture_compress": true, "texture_normal_map": false, "texture_detail_normal_map": false, "texture_create_mip_maps": true, "texture_wrap": true}}], "render_collides": true, "render_calculate_bounding_box": true, "render_nation_crest": false, "render_guild_crest": false, "render_bumped": false, "render_vp_active": false, "render_has_light_effects": false}, "702055": {"render_template": {"template_object_can_fade": true, "template_tracker": "NONE", "template_illuminated": false, "template_bone_length": 0.5806000232696533, "template_clip_map": 1, "template_light_two_side": 0, "template_cull_face": 1, "template_specular_map": 0, "template_shininess": 0.009999999776482582, "template_has_mesh": true, "template_mesh": {"mesh_set": [{"polymesh_id": 702055, "polymesh_decal": false, "polymesh_double_sided": false}]}}, "render_target_bone": "RRADIUS", "render_scale": [1.0, 1.0, 1.0], "render_has_loc": 1, "render_loc": [0.0, 0.0, 0.0], "render_children": [], "render_has_texture_set": true, "render_texture_set": [{"texture_type": "COLOR_TEXTURE", "texture_data": {"texture_id": 702050, "texture_transparent": "ALPHA", "texture_compress": true, "texture_normal_map": false, "texture_detail_normal_map": false, "texture_create_mip_maps": true, "texture_wrap": true}}], "render_collides": true, "render_calculate_bounding_box": true, "render_nation_crest": false, "render_guild_crest": false, "render_bumped": false, "render_vp_active": false, "render_has_light_effects": false}, "702056": {"render_template": {"template_object_can_fade": true, "template_tracker": "NONE", "template_illuminated": false, "template_bone_length": 0.0, "template_clip_map": 1, "template_light_two_side": 0, "template_cull_face": 1, "template_specular_map": 0, "template_shininess": 0.009999999776482582, "template_has_mesh": true, "template_mesh": {"mesh_set": [{"polymesh_id": 702056, "polymesh_decal": false, "polymesh_double_sided": false}]}}, "render_target_bone": "RWRIST", "render_scale": [1.0, 1.0, 1.0], "render_has_loc": 1, "render_loc": [0.0, 0.0, 0.0], "render_children": [], "render_has_texture_set": true, "render_texture_set": [{"texture_type": "COLOR_TEXTURE", "texture_data": {"texture_id": 702050, "texture_transparent": "ALPHA", "texture_compress": true, "texture_normal_map": false, "texture_detail_normal_map": false, "texture_create_mip_maps": true, "texture_wrap": true}}], "render_collides": true, "render_calculate_bounding_box": true, "render_nation_crest": false, "render_guild_crest": false, "render_bumped": false, "render_vp_active": false, "render_has_light_effects": false}, "702057": {"render_template": {"template_object_can_fade": true, "template_tracker": "NONE", "template_illuminated": false, "template_bone_length": 0.15699900686740875, "template_clip_map": 1, "template_light_two_side": 0, "template_cull_face": 1, "template_specular_map": 0, "template_shininess": 0.0, "template_has_mesh": true, "template_mesh": {"mesh_set": [{"polymesh_id": 702057, "polymesh_decal": false, "polymesh_double_sided": false}]}}, "render_target_bone": "NECKJOINT", "render_scale": [1.0, 1.0, 1.0], "render_has_loc": 1, "render_loc": [0.0, 0.0, 0.0], "render_children": [], "render_has_texture_set": false, "render_collides": true, "render_calculate_bounding_box": true, "render_nation_crest": false, "render_guild_crest": false, "render_bumped": false, "render_vp_active": false, "render_has_light_effects": false}, "702058": {"render_template": {"template_object_can_fade": true, "template_tracker": "NONE", "template_illuminated": false, "template_bone_length": 0.2379930019378662, "template_clip_map": 1, "template_light_two_side": 0, "template_cull_face": 1, "template_specular_map": 0, "template_shininess": 0.009999999776482582, "template_has_mesh": true, "template_mesh": {"mesh_set": [{"polymesh_id": 702058, "polymesh_decal": false, "polymesh_double_sided": false}]}}, "render_target_bone": "NECK", "render_scale": [1.0, 1.0, 1.0], "render_has_loc": 1, "render_loc": [0.0, 0.0, 0.0], "render_children": [], "render_has_texture_set": true, "render_texture_set": [{"texture_type": "COLOR_TEXTURE", "texture_data": {"texture_id": 702050, "texture_transparent": "ALPHA", "texture_compress": true, "texture_normal_map": false, "texture_detail_normal_map": false, "texture_create_mip_maps": true, "texture_wrap": true}}], "render_collides": true, "render_calculate_bounding_box": true, "render_nation_crest": false, "render_guild_crest": false, "render_bumped": false, "render_vp_active": false, "render_has_light_effects": false}, "702059": {"render_template": {"template_object_can_fade": true, "template_tracker": "NONE", "template_illuminated": false, "template_bone_length": 0.0, "template_clip_map": 1, "template_light_two_side": 0, "template_cull_face": 1, "template_specular_map": 0, "template_shininess": 0.009999999776482582, "template_has_mesh": true, "template_mesh": {"mesh_set": [{"polymesh_id": 702059, "polymesh_decal": false, "polymesh_double_sided": false}]}}, "render_target_bone": "HEAD", "render_scale": [1.0, 1.0, 1.0], "render_has_loc": 1, "render_loc": [0.0, 0.0, 0.0], "render_children": [], "render_has_texture_set": true, "render_texture_set": [{"texture_type": "COLOR_TEXTURE", "texture_data": {"texture_id": 702050, "texture_transparent": "ALPHA", "texture_compress": true, "texture_normal_map": false, "texture_detail_normal_map": false, "texture_create_mip_maps": true, "texture_wrap": true}}], "render_collides": true, "render_calculate_bounding_box": true, "render_nation_crest": false, "render_guild_crest": false, "render_bumped": false, "render_vp_active": false, "render_has_light_effects": false}, "702060": {"render_template": {"template_object_can_fade": true, "template_tracker": "NONE", "template_illuminated": false, "template_bone_length": 0.3459950089454651, "template_clip_map": 1, "template_light_two_side": 0, "template_cull_face": 1, "template_specular_map": 0, "template_shininess": 0.0, "template_has_mesh": true, "template_mesh": {"mesh_set": [{"polymesh_id": 702060, "polymesh_decal": false, "polymesh_double_sided": false}]}}, "render_target_bone": "RWINGJOINT", "render_scale": [1.0, 1.0, 1.0], "render_has_loc": 1, "render_loc": [0.0, 0.0, 0.0], "render_children": [], "render_has_texture_set": false, "render_collides": true, "render_calculate_bounding_box": true, "render_nation_crest": false, "render_guild_crest": false, "render_bumped": false, "render_vp_active": false, "render_has_light_effects": false}, "702061": {"render_template": {"template_object_can_fade": true, "template_tracker": "NONE", "template_illuminated": false, "template_bone_length": 0.5534210205078125, "template_clip_map": 1, "template_light_two_side": 0, "template_cull_face": 1, "template_specular_map": 0, "template_shininess": 0.009999999776482582, "template_has_mesh": true, "template_mesh": {"mesh_set": [{"polymesh_id": 702061, "polymesh_decal": false, "polymesh_double_sided": false}]}}, "render_target_bone": "RWING01", "render_scale": [1.0, 1.0, 1.0], "render_has_loc": 1, "render_loc": [0.0, 0.0, 0.0], "render_children": [], "render_has_texture_set": true, "render_texture_set": [{"texture_type": "COLOR_TEXTURE", "texture_data": {"texture_id": 702050, "texture_transparent": "ALPHA", "texture_compress": true, "texture_normal_map": false, "texture_detail_normal_map": false, "texture_create_mip_maps": true, "texture_wrap": true}}], "render_collides": true, "render_calculate_bounding_box": true, "render_nation_crest": false, "render_guild_crest": false, "render_bumped": false, "render_vp_active": false, "render_has_light_effects": false}, "702062": {"render_template": {"template_object_can_fade": true, "template_tracker": "NONE", "template_illuminated": false, "template_bone_length": 0.0, "template_clip_map": 1, "template_light_two_side": 0, "template_cull_face": 1, "template_specular_map": 0, "template_shininess": 0.009999999776482582, "template_has_mesh": true, "template_mesh": {"mesh_set": [{"polymesh_id": 702062, "polymesh_decal": false, "polymesh_double_sided": false}]}}, "render_target_bone": "RWING02", "render_scale": [1.0, 1.0, 1.0], "render_has_loc": 1, "render_loc": [0.0, 0.0, 0.0], "render_children": [], "render_has_texture_set": true, "render_texture_set": [{"texture_type": "COLOR_TEXTURE", "texture_data": {"texture_id": 702050, "texture_transparent": "ALPHA", "texture_compress": true, "texture_normal_map": false, "texture_detail_normal_map": false, "texture_create_mip_maps": true, "texture_wrap": true}}], "render_collides": true, "render_calculate_bounding_box": true, "render_nation_crest": false, "render_guild_crest": false, "render_bumped": false, "render_vp_active": false, "render_has_light_effects": false}, "702063": {"render_template": {"template_object_can_fade": true, "template_tracker": "NONE", "template_illuminated": false, "template_bone_length": 0.18787600100040436, "template_clip_map": 1, "template_light_two_side": 0, "template_cull_face": 1, "template_specular_map": 0, "template_shininess": 0.0, "template_has_mesh": true, "template_mesh": {"mesh_set": [{"polymesh_id": 6325, "polymesh_decal": false, "polymesh_double_sided": false}]}}, "render_target_bone": "RHIPJOINT", "render_scale": [1.0, 1.0, 1.0], "render_has_loc": 1, "render_loc": [0.0, 0.0, 0.0], "render_children": [], "render_has_texture_set": false, "render_collides": true, "render_calculate_bounding_box": true, "render_nation_crest": false, "render_guild_crest": false, "render_bumped": false, "render_vp_active": false, "render_has_light_effects": false}, "702064": {"render_template": {"template_object_can_fade": true, "template_tracker": "NONE", "template_illuminated": false, "template_bone_length": 0.9263989925384521, "template_clip_map": 1, "template_light_two_side": 0, "template_cull_face": 1, "template_specular_map": 0, "template_shininess": 0.009999999776482582, "template_has_mesh": true, "template_mesh": {"mesh_set": [{"polymesh_id": 702064, "polymesh_decal": false, "polymesh_double_sided": false}]}}, "render_target_bone": "RFEMUR", "render_scale": [1.0, 1.0, 1.0], "render_has_loc": 1, "render_loc": [0.0, 0.0, 0.0], "render_children": [], "render_has_texture_set": true, "render_texture_set": [{"texture_type": "COLOR_TEXTURE", "texture_data": {"texture_id": 702050, "texture_transparent": "ALPHA", "texture_compress": true, "texture_normal_map": false, "texture_detail_normal_map": false, "texture_create_mip_maps": true, "texture_wrap": true}}], "render_collides": true, "render_calculate_bounding_box": true, "render_nation_crest": false, "render_guild_crest": false, "render_bumped": false, "render_vp_active": false, "render_has_light_effects": false}, "702065": {"render_template": {"template_object_can_fade": true, "template_tracker": "NONE", "template_illuminated": false, "template_bone_length": 0.8621410131454468, "template_clip_map": 1, "template_light_two_side": 0, "template_cull_face": 1, "template_specular_map": 0, "template_shininess": 0.009999999776482582, "template_has_mesh": true, "template_mesh": {"mesh_set": [{"polymesh_id": 702065, "polymesh_decal": false, "polymesh_double_sided": false}]}}, "render_target_bone": "RTIBIA", "render_scale": [1.0, 1.0, 1.0], "render_has_loc": 1, "render_loc": [0.0, 0.0, 0.0], "render_children": [], "render_has_texture_set": true, "render_texture_set": [{"texture_type": "COLOR_TEXTURE", "texture_data": {"texture_id": 702050, "texture_transparent": "ALPHA", "texture_compress": true, "texture_normal_map": false, "texture_detail_normal_map": false, "texture_create_mip_maps": true, "texture_wrap": true}}], "render_collides": true, "render_calculate_bounding_box": true, "render_nation_crest": false, "render_guild_crest": false, "render_bumped": false, "render_vp_active": false, "render_has_light_effects": false}, "702066": {"render_template": {"template_object_can_fade": true, "template_tracker": "NONE", "template_illuminated": false, "template_bone_length": 0.413657009601593, "template_clip_map": 1, "template_light_two_side": 0, "template_cull_face": 1, "template_specular_map": 0, "template_shininess": 0.009999999776482582, "template_has_mesh": true, "template_mesh": {"mesh_set": [{"polymesh_id": 702066, "polymesh_decal": false, "polymesh_double_sided": false}]}}, "render_target_bone": "RFOOT", "render_scale": [1.0, 1.0, 1.0], "render_has_loc": 1, "render_loc": [0.0, 0.0, 0.0], "render_children": [], "render_has_texture_set": true, "render_texture_set": [{"texture_type": "COLOR_TEXTURE", "texture_data": {"texture_id": 702050, "texture_transparent": "ALPHA", "texture_compress": true, "texture_normal_map": false, "texture_detail_normal_map": false, "texture_create_mip_maps": true, "texture_wrap": true}}], "render_collides": true, "render_calculate_bounding_box": true, "render_nation_crest": false, "render_guild_crest": false, "render_bumped": false, "render_vp_active": false, "render_has_light_effects": false}, "702067": {"render_template": {"template_object_can_fade": true, "template_tracker": "NONE", "template_illuminated": false, "template_bone_length": 0.0, "template_clip_map": 1, "template_light_two_side": 0, "template_cull_face": 1, "template_specular_map": 0, "template_shininess": 0.009999999776482582, "template_has_mesh": true, "template_mesh": {"mesh_set": [{"polymesh_id": 702067, "polymesh_decal": false, "polymesh_double_sided": false}]}}, "render_target_bone": "RTOE", "render_scale": [1.0, 1.0, 1.0], "render_has_loc": 1, "render_loc": [0.0, 0.0, 0.0], "render_children": [], "render_has_texture_set": true, "render_texture_set": [{"texture_type": "COLOR_TEXTURE", "texture_data": {"texture_id": 702050, "texture_transparent": "ALPHA", "texture_compress": true, "texture_normal_map": false, "texture_detail_normal_map": false, "texture_create_mip_maps": true, "texture_wrap": true}}], "render_collides": true, "render_calculate_bounding_box": true, "render_nation_crest": false, "render_guild_crest": false, "render_bumped": false, "render_vp_active": false, "render_has_light_effects": false}}}