{"obj_name": "Snow Harpy", "body_part_renders": [706360, 706362, 706363, 706364, 706365, 706366, 706367, 706368, 706369, 706370, 706371, 706372, 706373, 706374, 706375, 706376, 706377, 706378, 706379, 706380, 706381, 706382], "render_data": {"706360": {"render_template": {"template_object_can_fade": true, "template_tracker": "NONE", "template_illuminated": false, "template_bone_length": 0.2750000059604645, "template_clip_map": 1, "template_light_two_side": 0, "template_cull_face": 0, "template_specular_map": 0, "template_shininess": 0.029999999329447746, "template_has_mesh": true, "template_mesh": {"mesh_set": [{"polymesh_id": 706361, "polymesh_decal": false, "polymesh_double_sided": false}]}}, "render_target_bone": "LOWERBACK", "render_scale": [1.0, 1.0, 1.0], "render_has_loc": 1, "render_loc": [0.0, 0.0, 0.0], "render_children": [], "render_has_texture_set": true, "render_texture_set": [{"texture_type": "COLOR_TEXTURE", "texture_data": {"texture_id": 706360, "texture_transparent": "ALPHA", "texture_compress": true, "texture_normal_map": false, "texture_detail_normal_map": false, "texture_create_mip_maps": true, "texture_wrap": true}}], "render_collides": true, "render_calculate_bounding_box": true, "render_nation_crest": false, "render_guild_crest": false, "render_bumped": false, "render_vp_active": false, "render_has_light_effects": false}, "706362": {"render_template": {"template_object_can_fade": true, "template_tracker": "NONE", "template_illuminated": false, "template_bone_length": 0.6958079934120178, "template_clip_map": 1, "template_light_two_side": 0, "template_cull_face": 0, "template_specular_map": 0, "template_shininess": 0.029999999329447746, "template_has_mesh": true, "template_mesh": {"mesh_set": [{"polymesh_id": 706362, "polymesh_decal": false, "polymesh_double_sided": false}]}}, "render_target_bone": "UPPERBACK", "render_scale": [1.0, 1.0, 1.0], "render_has_loc": 1, "render_loc": [0.0, 0.0, 0.0], "render_children": [], "render_has_texture_set": true, "render_texture_set": [{"texture_type": "COLOR_TEXTURE", "texture_data": {"texture_id": 706360, "texture_transparent": "ALPHA", "texture_compress": true, "texture_normal_map": false, "texture_detail_normal_map": false, "texture_create_mip_maps": true, "texture_wrap": true}}], "render_collides": true, "render_calculate_bounding_box": true, "render_nation_crest": false, "render_guild_crest": false, "render_bumped": false, "render_vp_active": false, "render_has_light_effects": false}, "706363": {"render_template": {"template_object_can_fade": true, "template_tracker": "NONE", "template_illuminated": false, "template_bone_length": 0.29146701097488403, "template_clip_map": 1, "template_light_two_side": 0, "template_cull_face": 0, "template_specular_map": 0, "template_shininess": 0.029999999329447746, "template_has_mesh": true, "template_mesh": {"mesh_set": [{"polymesh_id": 706363, "polymesh_decal": false, "polymesh_double_sided": false}]}}, "render_target_bone": "NECK", "render_scale": [1.0, 1.0, 1.0], "render_has_loc": 1, "render_loc": [0.0, 0.0, 0.0], "render_children": [], "render_has_texture_set": true, "render_texture_set": [{"texture_type": "COLOR_TEXTURE", "texture_data": {"texture_id": 706360, "texture_transparent": "ALPHA", "texture_compress": true, "texture_normal_map": false, "texture_detail_normal_map": false, "texture_create_mip_maps": true, "texture_wrap": true}}], "render_collides": true, "render_calculate_bounding_box": true, "render_nation_crest": false, "render_guild_crest": false, "render_bumped": false, "render_vp_active": false, "render_has_light_effects": false}, "706364": {"render_template": {"template_object_can_fade": true, "template_tracker": "NONE", "template_illuminated": false, "template_bone_length": 0.0, "template_clip_map": 1, "template_light_two_side": 0, "template_cull_face": 0, "template_specular_map": 0, "template_shininess": 0.029999999329447746, "template_has_mesh": true, "template_mesh": {"mesh_set": [{"polymesh_id": 706364, "polymesh_decal": false, "polymesh_double_sided": false}]}}, "render_target_bone": "HEAD", "render_scale": [1.0, 1.0, 1.0], "render_has_loc": 1, "render_loc": [0.0, 0.0, 0.0], "render_children": [], "render_has_texture_set": true, "render_texture_set": [{"texture_type": "COLOR_TEXTURE", "texture_data": {"texture_id": 706360, "texture_transparent": "ALPHA", "texture_compress": true, "texture_normal_map": false, "texture_detail_normal_map": false, "texture_create_mip_maps": true, "texture_wrap": true}}], "render_collides": true, "render_calculate_bounding_box": true, "render_nation_crest": false, "render_guild_crest": false, "render_bumped": false, "render_vp_active": false, "render_has_light_effects": false}, "706365": {"render_template": {"template_object_can_fade": true, "template_tracker": "NONE", "template_illuminated": false, "template_bone_length": 0.221329003572464, "template_clip_map": 1, "template_light_two_side": 0, "template_cull_face": 1, "template_specular_map": 0, "template_shininess": 0.0, "template_has_mesh": true, "template_mesh": {"mesh_set": [{"polymesh_id": 706365, "polymesh_decal": false, "polymesh_double_sided": false}]}}, "render_target_bone": "RWINGJOINT", "render_scale": [1.0, 1.0, 1.0], "render_has_loc": 1, "render_loc": [0.0, 0.0, 0.0], "render_children": [], "render_has_texture_set": false, "render_collides": true, "render_calculate_bounding_box": true, "render_nation_crest": false, "render_guild_crest": false, "render_bumped": false, "render_vp_active": false, "render_has_light_effects": false}, "706366": {"render_template": {"template_object_can_fade": true, "template_tracker": "NONE", "template_illuminated": false, "template_bone_length": 0.9497380256652832, "template_clip_map": 1, "template_light_two_side": 0, "template_cull_face": 1, "template_specular_map": 0, "template_shininess": 0.029999999329447746, "template_has_mesh": true, "template_mesh": {"mesh_set": [{"polymesh_id": 706366, "polymesh_decal": false, "polymesh_double_sided": false}]}}, "render_target_bone": "RWING01", "render_scale": [1.0, 1.0, 1.0], "render_has_loc": 1, "render_loc": [0.0, 0.0, 0.0], "render_children": [], "render_has_texture_set": true, "render_texture_set": [{"texture_type": "COLOR_TEXTURE", "texture_data": {"texture_id": 706361, "texture_transparent": "ALPHA", "texture_compress": true, "texture_normal_map": false, "texture_detail_normal_map": false, "texture_create_mip_maps": true, "texture_wrap": true}}], "render_collides": true, "render_calculate_bounding_box": true, "render_nation_crest": false, "render_guild_crest": false, "render_bumped": false, "render_vp_active": false, "render_has_light_effects": false}, "706367": {"render_template": {"template_object_can_fade": true, "template_tracker": "NONE", "template_illuminated": false, "template_bone_length": 0.0, "template_clip_map": 1, "template_light_two_side": 0, "template_cull_face": 1, "template_specular_map": 0, "template_shininess": 0.029999999329447746, "template_has_mesh": true, "template_mesh": {"mesh_set": [{"polymesh_id": 706367, "polymesh_decal": false, "polymesh_double_sided": false}]}}, "render_target_bone": "RWING02", "render_scale": [1.0, 1.0, 1.0], "render_has_loc": 1, "render_loc": [0.0, 0.0, 0.0], "render_children": [], "render_has_texture_set": true, "render_texture_set": [{"texture_type": "COLOR_TEXTURE", "texture_data": {"texture_id": 706361, "texture_transparent": "ALPHA", "texture_compress": true, "texture_normal_map": false, "texture_detail_normal_map": false, "texture_create_mip_maps": true, "texture_wrap": true}}], "render_collides": true, "render_calculate_bounding_box": true, "render_nation_crest": false, "render_guild_crest": false, "render_bumped": false, "render_vp_active": false, "render_has_light_effects": false}, "706368": {"render_template": {"template_object_can_fade": true, "template_tracker": "NONE", "template_illuminated": false, "template_bone_length": 0.0, "template_clip_map": 1, "template_light_two_side": 0, "template_cull_face": 1, "template_specular_map": 0, "template_shininess": 0.029999999329447746, "template_has_mesh": true, "template_mesh": {"mesh_set": [{"polymesh_id": 706368, "polymesh_decal": false, "polymesh_double_sided": false}]}}, "render_target_bone": "RWING03", "render_scale": [1.0, 1.0, 1.0], "render_has_loc": 1, "render_loc": [0.0, 0.0, 0.0], "render_children": [], "render_has_texture_set": true, "render_texture_set": [{"texture_type": "COLOR_TEXTURE", "texture_data": {"texture_id": 706361, "texture_transparent": "ALPHA", "texture_compress": true, "texture_normal_map": false, "texture_detail_normal_map": false, "texture_create_mip_maps": true, "texture_wrap": true}}], "render_collides": true, "render_calculate_bounding_box": true, "render_nation_crest": false, "render_guild_crest": false, "render_bumped": false, "render_vp_active": false, "render_has_light_effects": false}, "706369": {"render_template": {"template_object_can_fade": true, "template_tracker": "NONE", "template_illuminated": false, "template_bone_length": 0.0, "template_clip_map": 1, "template_light_two_side": 0, "template_cull_face": 1, "template_specular_map": 0, "template_shininess": 0.029999999329447746, "template_has_mesh": true, "template_mesh": {"mesh_set": [{"polymesh_id": 706369, "polymesh_decal": false, "polymesh_double_sided": false}]}}, "render_target_bone": "RWING04", "render_scale": [1.0, 1.0, 1.0], "render_has_loc": 1, "render_loc": [0.0, 0.0, 0.0], "render_children": [], "render_has_texture_set": true, "render_texture_set": [{"texture_type": "COLOR_TEXTURE", "texture_data": {"texture_id": 706361, "texture_transparent": "ALPHA", "texture_compress": true, "texture_normal_map": false, "texture_detail_normal_map": false, "texture_create_mip_maps": true, "texture_wrap": true}}], "render_collides": true, "render_calculate_bounding_box": true, "render_nation_crest": false, "render_guild_crest": false, "render_bumped": false, "render_vp_active": false, "render_has_light_effects": false}, "706370": {"render_template": {"template_object_can_fade": true, "template_tracker": "NONE", "template_illuminated": false, "template_bone_length": 0.15980100631713867, "template_clip_map": 1, "template_light_two_side": 0, "template_cull_face": 1, "template_specular_map": 0, "template_shininess": 0.0, "template_has_mesh": true, "template_mesh": {"mesh_set": [{"polymesh_id": 706370, "polymesh_decal": false, "polymesh_double_sided": false}]}}, "render_target_bone": "RHIPJOINT", "render_scale": [1.0, 1.0, 1.0], "render_has_loc": 1, "render_loc": [0.0, 0.0, 0.0], "render_children": [], "render_has_texture_set": false, "render_collides": true, "render_calculate_bounding_box": true, "render_nation_crest": false, "render_guild_crest": false, "render_bumped": false, "render_vp_active": false, "render_has_light_effects": false}, "706371": {"render_template": {"template_object_can_fade": true, "template_tracker": "NONE", "template_illuminated": false, "template_bone_length": 0.5416100025177002, "template_clip_map": 1, "template_light_two_side": 0, "template_cull_face": 0, "template_specular_map": 0, "template_shininess": 0.029999999329447746, "template_has_mesh": true, "template_mesh": {"mesh_set": [{"polymesh_id": 706371, "polymesh_decal": false, "polymesh_double_sided": false}]}}, "render_target_bone": "RHIP", "render_scale": [1.0, 1.0, 1.0], "render_has_loc": 1, "render_loc": [0.0, 0.0, 0.0], "render_children": [], "render_has_texture_set": true, "render_texture_set": [{"texture_type": "COLOR_TEXTURE", "texture_data": {"texture_id": 706360, "texture_transparent": "ALPHA", "texture_compress": true, "texture_normal_map": false, "texture_detail_normal_map": false, "texture_create_mip_maps": true, "texture_wrap": true}}], "render_collides": true, "render_calculate_bounding_box": true, "render_nation_crest": false, "render_guild_crest": false, "render_bumped": false, "render_vp_active": false, "render_has_light_effects": false}, "706372": {"render_template": {"template_object_can_fade": true, "template_tracker": "NONE", "template_illuminated": false, "template_bone_length": 0.5667870044708252, "template_clip_map": 1, "template_light_two_side": 0, "template_cull_face": 0, "template_specular_map": 0, "template_shininess": 0.029999999329447746, "template_has_mesh": true, "template_mesh": {"mesh_set": [{"polymesh_id": 706372, "polymesh_decal": false, "polymesh_double_sided": false}]}}, "render_target_bone": "RFEMUR", "render_scale": [1.0, 1.0, 1.0], "render_has_loc": 1, "render_loc": [0.0, 0.0, 0.0], "render_children": [], "render_has_texture_set": true, "render_texture_set": [{"texture_type": "COLOR_TEXTURE", "texture_data": {"texture_id": 706360, "texture_transparent": "ALPHA", "texture_compress": true, "texture_normal_map": false, "texture_detail_normal_map": false, "texture_create_mip_maps": true, "texture_wrap": true}}], "render_collides": true, "render_calculate_bounding_box": true, "render_nation_crest": false, "render_guild_crest": false, "render_bumped": false, "render_vp_active": false, "render_has_light_effects": false}, "706373": {"render_template": {"template_object_can_fade": true, "template_tracker": "NONE", "template_illuminated": false, "template_bone_length": 0.6835619807243347, "template_clip_map": 1, "template_light_two_side": 0, "template_cull_face": 0, "template_specular_map": 0, "template_shininess": 0.029999999329447746, "template_has_mesh": true, "template_mesh": {"mesh_set": [{"polymesh_id": 706373, "polymesh_decal": false, "polymesh_double_sided": false}]}}, "render_target_bone": "RTIBIA", "render_scale": [1.0, 1.0, 1.0], "render_has_loc": 1, "render_loc": [0.0, 0.0, 0.0], "render_children": [], "render_has_texture_set": true, "render_texture_set": [{"texture_type": "COLOR_TEXTURE", "texture_data": {"texture_id": 706360, "texture_transparent": "ALPHA", "texture_compress": true, "texture_normal_map": false, "texture_detail_normal_map": false, "texture_create_mip_maps": true, "texture_wrap": true}}], "render_collides": true, "render_calculate_bounding_box": true, "render_nation_crest": false, "render_guild_crest": false, "render_bumped": false, "render_vp_active": false, "render_has_light_effects": false}, "706374": {"render_template": {"template_object_can_fade": true, "template_tracker": "NONE", "template_illuminated": false, "template_bone_length": 0.2684920132160187, "template_clip_map": 1, "template_light_two_side": 0, "template_cull_face": 0, "template_specular_map": 0, "template_shininess": 0.029999999329447746, "template_has_mesh": true, "template_mesh": {"mesh_set": [{"polymesh_id": 706374, "polymesh_decal": false, "polymesh_double_sided": false}]}}, "render_target_bone": "RFOOT", "render_scale": [1.0, 1.0, 1.0], "render_has_loc": 1, "render_loc": [0.0, 0.0, 0.0], "render_children": [], "render_has_texture_set": true, "render_texture_set": [{"texture_type": "COLOR_TEXTURE", "texture_data": {"texture_id": 706360, "texture_transparent": "ALPHA", "texture_compress": true, "texture_normal_map": false, "texture_detail_normal_map": false, "texture_create_mip_maps": true, "texture_wrap": true}}], "render_collides": true, "render_calculate_bounding_box": true, "render_nation_crest": false, "render_guild_crest": false, "render_bumped": false, "render_vp_active": false, "render_has_light_effects": false}, "706375": {"render_template": {"template_object_can_fade": true, "template_tracker": "NONE", "template_illuminated": false, "template_bone_length": 0.0, "template_clip_map": 1, "template_light_two_side": 0, "template_cull_face": 0, "template_specular_map": 0, "template_shininess": 0.029999999329447746, "template_has_mesh": true, "template_mesh": {"mesh_set": [{"polymesh_id": 706375, "polymesh_decal": false, "polymesh_double_sided": false}]}}, "render_target_bone": "RTOE", "render_scale": [1.0, 1.0, 1.0], "render_has_loc": 1, "render_loc": [0.0, 0.0, 0.0], "render_children": [], "render_has_texture_set": true, "render_texture_set": [{"texture_type": "COLOR_TEXTURE", "texture_data": {"texture_id": 706360, "texture_transparent": "ALPHA", "texture_compress": true, "texture_normal_map": false, "texture_detail_normal_map": false, "texture_create_mip_maps": true, "texture_wrap": true}}], "render_collides": true, "render_calculate_bounding_box": true, "render_nation_crest": false, "render_guild_crest": false, "render_bumped": false, "render_vp_active": false, "render_has_light_effects": false}, "706376": {"render_template": {"template_object_can_fade": true, "template_tracker": "NONE", "template_illuminated": false, "template_bone_length": 0.19787399470806122, "template_clip_map": 1, "template_light_two_side": 0, "template_cull_face": 1, "template_specular_map": 0, "template_shininess": 0.0, "template_has_mesh": true, "template_mesh": {"mesh_set": [{"polymesh_id": 706370, "polymesh_decal": false, "polymesh_double_sided": false}]}}, "render_target_bone": "TAILJOINT", "render_scale": [1.0, 1.0, 1.0], "render_has_loc": 1, "render_loc": [0.0, 0.0, 0.0], "render_children": [], "render_has_texture_set": false, "render_collides": true, "render_calculate_bounding_box": true, "render_nation_crest": false, "render_guild_crest": false, "render_bumped": false, "render_vp_active": false, "render_has_light_effects": false}, "706377": {"render_template": {"template_object_can_fade": true, "template_tracker": "NONE", "template_illuminated": false, "template_bone_length": 0.6454010009765625, "template_clip_map": 1, "template_light_two_side": 0, "template_cull_face": 0, "template_specular_map": 0, "template_shininess": 0.029999999329447746, "template_has_mesh": true, "template_mesh": {"mesh_set": [{"polymesh_id": 706377, "polymesh_decal": false, "polymesh_double_sided": false}]}}, "render_target_bone": "TAIL01", "render_scale": [1.0, 1.0, 1.0], "render_has_loc": 1, "render_loc": [0.0, 0.0, 0.0], "render_children": [], "render_has_texture_set": true, "render_texture_set": [{"texture_type": "COLOR_TEXTURE", "texture_data": {"texture_id": 706360, "texture_transparent": "ALPHA", "texture_compress": true, "texture_normal_map": false, "texture_detail_normal_map": false, "texture_create_mip_maps": true, "texture_wrap": true}}], "render_collides": true, "render_calculate_bounding_box": true, "render_nation_crest": false, "render_guild_crest": false, "render_bumped": false, "render_vp_active": false, "render_has_light_effects": false}, "706378": {"render_template": {"template_object_can_fade": true, "template_tracker": "NONE", "template_illuminated": false, "template_bone_length": 0.40864700078964233, "template_clip_map": 1, "template_light_two_side": 0, "template_cull_face": 0, "template_specular_map": 0, "template_shininess": 0.029999999329447746, "template_has_mesh": true, "template_mesh": {"mesh_set": [{"polymesh_id": 706378, "polymesh_decal": false, "polymesh_double_sided": false}]}}, "render_target_bone": "TAIL02", "render_scale": [1.0, 1.0, 1.0], "render_has_loc": 1, "render_loc": [0.0, 0.0, 0.0], "render_children": [], "render_has_texture_set": true, "render_texture_set": [{"texture_type": "COLOR_TEXTURE", "texture_data": {"texture_id": 706360, "texture_transparent": "ALPHA", "texture_compress": true, "texture_normal_map": false, "texture_detail_normal_map": false, "texture_create_mip_maps": true, "texture_wrap": true}}], "render_collides": true, "render_calculate_bounding_box": true, "render_nation_crest": false, "render_guild_crest": false, "render_bumped": false, "render_vp_active": false, "render_has_light_effects": false}, "706379": {"render_template": {"template_object_can_fade": true, "template_tracker": "NONE", "template_illuminated": false, "template_bone_length": 0.4075849950313568, "template_clip_map": 1, "template_light_two_side": 0, "template_cull_face": 0, "template_specular_map": 0, "template_shininess": 0.029999999329447746, "template_has_mesh": true, "template_mesh": {"mesh_set": [{"polymesh_id": 706379, "polymesh_decal": false, "polymesh_double_sided": false}]}}, "render_target_bone": "TAIL03", "render_scale": [1.0, 1.0, 1.0], "render_has_loc": 1, "render_loc": [0.0, 0.0, 0.0], "render_children": [], "render_has_texture_set": true, "render_texture_set": [{"texture_type": "COLOR_TEXTURE", "texture_data": {"texture_id": 706360, "texture_transparent": "ALPHA", "texture_compress": true, "texture_normal_map": false, "texture_detail_normal_map": false, "texture_create_mip_maps": true, "texture_wrap": true}}], "render_collides": true, "render_calculate_bounding_box": true, "render_nation_crest": false, "render_guild_crest": false, "render_bumped": false, "render_vp_active": false, "render_has_light_effects": false}, "706380": {"render_template": {"template_object_can_fade": true, "template_tracker": "NONE", "template_illuminated": false, "template_bone_length": 0.41572800278663635, "template_clip_map": 1, "template_light_two_side": 0, "template_cull_face": 0, "template_specular_map": 0, "template_shininess": 0.029999999329447746, "template_has_mesh": true, "template_mesh": {"mesh_set": [{"polymesh_id": 706380, "polymesh_decal": false, "polymesh_double_sided": false}]}}, "render_target_bone": "TAIL04", "render_scale": [1.0, 1.0, 1.0], "render_has_loc": 1, "render_loc": [0.0, 0.0, 0.0], "render_children": [], "render_has_texture_set": true, "render_texture_set": [{"texture_type": "COLOR_TEXTURE", "texture_data": {"texture_id": 706360, "texture_transparent": "ALPHA", "texture_compress": true, "texture_normal_map": false, "texture_detail_normal_map": false, "texture_create_mip_maps": true, "texture_wrap": true}}], "render_collides": true, "render_calculate_bounding_box": true, "render_nation_crest": false, "render_guild_crest": false, "render_bumped": false, "render_vp_active": false, "render_has_light_effects": false}, "706381": {"render_template": {"template_object_can_fade": true, "template_tracker": "NONE", "template_illuminated": false, "template_bone_length": 0.41460898518562317, "template_clip_map": 1, "template_light_two_side": 0, "template_cull_face": 0, "template_specular_map": 0, "template_shininess": 0.029999999329447746, "template_has_mesh": true, "template_mesh": {"mesh_set": [{"polymesh_id": 706381, "polymesh_decal": false, "polymesh_double_sided": false}]}}, "render_target_bone": "TAIL05", "render_scale": [1.0, 1.0, 1.0], "render_has_loc": 1, "render_loc": [0.0, 0.0, 0.0], "render_children": [], "render_has_texture_set": true, "render_texture_set": [{"texture_type": "COLOR_TEXTURE", "texture_data": {"texture_id": 706360, "texture_transparent": "ALPHA", "texture_compress": true, "texture_normal_map": false, "texture_detail_normal_map": false, "texture_create_mip_maps": true, "texture_wrap": true}}], "render_collides": true, "render_calculate_bounding_box": true, "render_nation_crest": false, "render_guild_crest": false, "render_bumped": false, "render_vp_active": false, "render_has_light_effects": false}, "706382": {"render_template": {"template_object_can_fade": true, "template_tracker": "NONE", "template_illuminated": false, "template_bone_length": 0.0, "template_clip_map": 1, "template_light_two_side": 0, "template_cull_face": 0, "template_specular_map": 0, "template_shininess": 0.029999999329447746, "template_has_mesh": true, "template_mesh": {"mesh_set": [{"polymesh_id": 706382, "polymesh_decal": false, "polymesh_double_sided": false}]}}, "render_target_bone": "TAIL06", "render_scale": [1.0, 1.0, 1.0], "render_has_loc": 1, "render_loc": [0.0, 0.0, 0.0], "render_children": [], "render_has_texture_set": true, "render_texture_set": [{"texture_type": "COLOR_TEXTURE", "texture_data": {"texture_id": 706360, "texture_transparent": "ALPHA", "texture_compress": true, "texture_normal_map": false, "texture_detail_normal_map": false, "texture_create_mip_maps": true, "texture_wrap": true}}], "render_collides": true, "render_calculate_bounding_box": true, "render_nation_crest": false, "render_guild_crest": false, "render_bumped": false, "render_vp_active": false, "render_has_light_effects": false}}}